Py_Focus/__init__.py
Py_Focus/plot.py
Py_Focus/sim.py
Py_Focus/user_interface.py
Py_Focus-0.1.dist-info/LICENCE.txt
Py_Focus-0.1.dist-info/METADATA
Py_Focus-0.1.dist-info/WHEEL
Py_Focus-0.1.dist-info/top_level.txt
Py_Focus-0.1.dist-info/RECORD
