Metadata-Version: 2.1
Name: Py-Focus
Version: 0.1
Summary: Full vectorial calculation of focused electromagnetic fields moduled by a custom phase mask
Home-page: https://github.com/fcaprile/Py_Focus
Author: Caprile Fernando
Author-email: fcaprile@gmail.com
License: MIT
Download-URL: https://github.com/fcaprile/Py_Focus/archive/refs/tags/0.1.tar.gz
Keywords: User interface,Custom phase mask
Platform: UNKNOWN
Classifier: Development Status :: 3 - Alpha
Classifier: Intended Audience :: Developers
Classifier: Topic :: Software Development :: Build Tools
Classifier: License :: OSI Approved :: MIT License
Classifier: Programming Language :: Python :: 3
Classifier: Programming Language :: Python :: 3.4
Classifier: Programming Language :: Python :: 3.5
Classifier: Programming Language :: Python :: 3.6
License-File: LICENCE.txt
Requires-Dist: config
Requires-Dist: tqdm
Requires-Dist: numpy
Requires-Dist: matplotlib
Requires-Dist: scipy
Requires-Dist: PyQt5
Requires-Dist: qtpy
Requires-Dist: pyqtgraph
Requires-Dist: qdarkstyle
Requires-Dist: os
Requires-Dist: configparser
Requires-Dist: time
